[{"name": "", "price": null, "status": null, "shipping": null, "free_returns": false, "items_sold": null}, {"name": "Apple Watch Series 3 GPS+LTE w/ 42MM Space Gray Aluminum Case & Black Band", "price": 15995, "status": "Pre-Owned", "shipping": 0, "free_returns": true, "items_sold": 796}, {"name": "Apple Watch Series 4 GPS+LTE w/ 40MM Gold Aluminum Case & Pink Sand Sport Band", "price": 18995, "status": "Pre-Owned", "shipping": 0, "free_returns": true, "items_sold": 57}, {"name": "Apple Watch Series 6 40mm GPS Gold Aluminum Case Sport Band MG123LL/A", "price": 30900, "status": "Open Box", "shipping": null, "free_returns": true, "items_sold": 4001}, {"name": "Apple Watch Series 4 44mm Space Gray Case Black Sport Band GPS + LTE (MTUW2LL/A)", "price": 17499, "status": "Pre-Owned", "shipping": 0, "free_returns": true, "items_sold": 84}, {"name": "Apple Watch SE (GPS) 44mm Aluminum Case Black Sport Band - Space Gray MYDT2LL/A", "price": 25500, "status": "Open Box", "shipping": null, "free_returns": true, "items_sold": 0}, {"name": "Apple Watch Series 3 38mm 42mm GPS + WiFi + Cellular Smart Watch All Colors!", "price": 10999, "status": "Refurbished", "shipping": 0, "free_returns": true, "items_sold": 538}, {"name": "Apple Watch Series 6 (GPS) 44mm with Black Sport Band - Space Gray M00H3LL/A", "price": 34900, "status": "Open Box", "shipping": null, "free_returns": true, "items_sold": 0}, {"name": "Apple Watch Series 6 (GPS, 44mm, Blue Aluminum, Deep Navy Sport Band) M00J3LL/A", "price": 33900, "status": "Open Box", "shipping": null, "free_returns": true, "items_sold": 0}, {"name": "Apple Watch Series 4 40mm 44mm GPS + WiFi + Cellular Smart Watch, All Colors!", "price": 15999, "status": "Refurbished", "shipping": 0, "free_returns": true, "items_sold": 1367}, {"name": "Apple Watch Series 6 44mm 32GB Space Gray Aluminum Case Black Sport Band", "price": 25495, "status": "Pre-Owned", "shipping": 0, "free_returns": true, "items_sold": 0}, {"name": "New ListingApple Watch Series 5 \u2013 Space Gray Aluminum Case (40mm) \u2013 GPS & Cellular", "price": 9100, "status": "Pre-Owned", "shipping": 1595, "free_returns": false, "items_sold": null}, {"name": "Apple Watch Series 3 42mm Space Gray Case Black Sport Band GPS + Cellular Used", "price": 13499, "status": "Pre-Owned", "shipping": 0, "free_returns": true, "items_sold": 587}, {"name": "New ListingApple Watch Series 5 44mm GPS LTE Cellular Space Gray", "price": 20000, "status": "Pre-Owned", "shipping": 800, "free_returns": false, "items_sold": null}, {"name": "Apple Watch Series 3 - 38MM / 42MM GPS / Cellular - All Colors", "price": 10899, "status": "Refurbished", "shipping": 0, "free_returns": true, "items_sold": 550}, {"name": "NEW Apple Watch Series 1, 2, 3, 4, 5, 6, Watch SE 38/42/40/44mm GPS or Cellular", "price": 13995, "status": "Open Box", "shipping": 0, "free_returns": true, "items_sold": 13}, {"name": "Apple Watch Series 4 44mm Silver Aluminum Case, White Sport Band (GPS + CELL)", "price": 16999, "status": "Pre-Owned", "shipping": 0, "free_returns": true, "items_sold": 23}, {"name": "Apple Watch Series 4 40mm Gold Aluminum Case Pink Sand Sport Band (GPS + CELL)", "price": 16999, "status": "Pre-Owned", "shipping": 0, "free_returns": true, "items_sold": 0}, {"name": "Apple Watch Series 3 GPS 38mm Space Gray Aluminum Case w/ Black Band BRAND NEW!", "price": 19895, "status": "Brand New", "shipping": 0, "free_returns": true, "items_sold": 183}, {"name": "Apple Watch Series 3, Aluminum Case - 38MM / 42MM, GPS / Cellular - All Colors", "price": 11999, "status": "Pre-Owned", "shipping": 0, "free_returns": true, "items_sold": 0}, {"name": "Apple Watch Gen 3 Series 3 38mm Silver Aluminum - White Sport Band MTEY2LL/A", "price": 14900, "status": "Refurbished", "shipping": 0, "free_returns": true, "items_sold": 0}, {"name": "apple watch series 1 38mm", "price": 4000, "status": "Pre-Owned", "shipping": 1200, "free_returns": false, "items_sold": null}, {"name": "Apple Watch Series 6 40MM GPS Aluminum Case w/ Navy Sport Band MG143LL/A", "price": 32900, "status": "Open Box", "shipping": null, "free_returns": true, "items_sold": 0}, {"name": "New ListingApple Watch series 5 44mm gps cellular", "price": 19000, "status": "Pre-Owned", "shipping": 540, "free_returns": false, "items_sold": null}, {"name": "Apple Watch Series 2 - 38mm - Rose Aluminum Case - Pink Sport Band - Smartwatch", "price": 8499, "status": "Open Box", "shipping": 0, "free_returns": true, "items_sold": 24}, {"name": "New Listingapple watch series 3 38mm", "price": 10400, "status": "Pre-Owned", "shipping": 475, "free_returns": false, "items_sold": null}, {"name": "Apple Watch Series 4 40mm 44mm GPS + Cellular 4G LTE - Gold Space Gray Silver", "price": 17499, "status": "Refurbished", "shipping": null, "free_returns": true, "items_sold": 185}, {"name": "New ListingApple Watch Series 5 44mm Space Gray Aluminum - W/Black Sport Bands - S/M & M/L", "price": 13000, "status": "Pre-Owned", "shipping": 1500, "free_returns": false, "items_sold": null}, {"name": "New ListingApple Watch Series 5 44mm Space Gray Aluminum Case Black Sport Band GPS + LTE", "price": 18999, "status": "Pre-Owned", "shipping": 0, "free_returns": false, "items_sold": null}, {"name": "Apple Watch Series 6 5 4 SE 3D Edge Tempered Glass Full Screen Protector 40/44mm", "price": 199, "status": "Brand New", "shipping": 259, "free_returns": false, "items_sold": 470}, {"name": "NEW Apple\u00a0Watch Series 3 (GPS) 38mm Space Gray Aluminum Case w/ Black Sport Band", "price": 23499, "status": "Brand New", "shipping": 0, "free_returns": true, "items_sold": null}, {"name": "New ListingApple Watch Series 5 44mm Space Gray Aluminum Case Black Sport Band GPS + LTE", "price": 18999, "status": "Pre-Owned", "shipping": 0, "free_returns": false, "items_sold": null}, {"name": "Apple Watch SE 40mm 44mm GPS + Cellular  LTE Gold Space Gray Silver Pristine", "price": 23999, "status": "Open Box", "shipping": null, "free_returns": true, "items_sold": 64}, {"name": "Apple Watch Series 5 40mm 44mm GPS + WiFi + Cellular Smart Watch", "price": 20999, "status": "Refurbished", "shipping": 0, "free_returns": true, "items_sold": 162}, {"name": "Apple Watch Series 4 40 mm Space Gray Case with Black Sport Band GPS + Cellular", "price": 17999, "status": "Pre-Owned", "shipping": null, "free_returns": true, "items_sold": 0}, {"name": "New ListingApple Watch Series 6 Blue 44mm GPS+CELLULAR", "price": 17500, "status": "Pre-Owned", "shipping": 550, "free_returns": false, "items_sold": null}, {"name": "Apple Watch Series 2  38/42MM Smartwatch + Sport Band Aluminum / Stainless Case", "price": 8499, "status": "Open Box", "shipping": 0, "free_returns": true, "items_sold": 132}, {"name": "New ListingApple Watch Series 3 38 mm Silver Aluminum Case White Sport Band Smartwatch -...", "price": 12000, "status": "Pre-Owned", "shipping": 0, "free_returns": false, "items_sold": null}, {"name": "New ListingApple Watch SE 40mm Gold Aluminum Case with Pink Sand Sport Band - Regular (GPS)", "price": 24900, "status": "Brand New", "shipping": 1465, "free_returns": false, "items_sold": null}, {"name": "NEW Apple Watch SE Series 2 Series 3 Series 4 Series 5 Series 6 38/42/40/44 ", "price": 11995, "status": "Open Box", "shipping": 0, "free_returns": true, "items_sold": 51}, {"name": "Apple Watch SE GPS, 40mm Space Gray Aluminum Case with Black Sport Band", "price": 19999, "status": "Pre-Owned", "shipping": 0, "free_returns": true, "items_sold": 0}, {"name": "New ListingApple watch series 5 44mm Space Gray Anchor Gray Sport Loop Band", "price": 20000, "status": "Pre-Owned", "shipping": 540, "free_returns": false, "items_sold": null}, {"name": "Apple Watch Series 3 38 mm Gray Case Black Aluminium Smartwatch PRISTINE IN BOX", "price": 14499, "status": "Open Box", "shipping": 0, "free_returns": true, "items_sold": 2733}, {"name": "Apple Watch Series 4 40 mm Space Gray Aluminum Case (GPS + Cellular)", "price": 6100, "status": "Pre-Owned", "shipping": 870, "free_returns": false, "items_sold": null}, {"name": "New ListingApple Watch Series 4 44mm Space Gray GPS  Sport Band", "price": 15999, "status": "Pre-Owned", "shipping": null, "free_returns": false, "items_sold": null}, {"name": "Apple Watch Series 3 42 mm Gray Case Black Aluminium Smartwatch Mint", "price": 15999, "status": "Open Box", "shipping": 0, "free_returns": true, "items_sold": 92}, {"name": "New Listingapple watch series 3 38mm", "price": 8500, "status": "Refurbished", "shipping": 430, "free_returns": false, "items_sold": null}, {"name": "Apple Watch Series 6 GPS 40mm Space Gray Aluminum Black Sport Band MG133LL/A", "price": 33900, "status": "Open Box", "shipping": null, "free_returns": true, "items_sold": 0}, {"name": "New ListingApple Watch Series 3 GPS 42mm Silver Aluminum Case Nike Sports Band - MTF22LL/A", "price": 10800, "status": "Pre-Owned", "shipping": 1465, "free_returns": false, "items_sold": null}, {"name": "New ListingApple Watch SE 40mm Gold Case With Pink Sand Sport Band ", "price": 20000, "status": "Open Box", "shipping": 1399, "free_returns": false, "items_sold": null}, {"name": "Apple Watch Series 5 44mm Space Gray Aluminum Case Black Sport Band (GPS + LTE)", "price": 18050, "status": "Pre-Owned", "shipping": 550, "free_returns": false, "items_sold": null}, {"name": "Apple Watch Series 4  40MM 44MM  GPS / Cellular Smart Watch - All Colors!", "price": 16499, "status": "Refurbished", "shipping": 0, "free_returns": true, "items_sold": 460}, {"name": "Apple Watch Series 4 40mm Gold Case Pink Sand Sport Band GPS + Cellular Used", "price": 17499, "status": "Pre-Owned", "shipping": 0, "free_returns": true, "items_sold": 301}, {"name": "Apple Watch Series 2 Smartwatch with Sport Band", "price": 8999, "status": "Refurbished", "shipping": 0, "free_returns": true, "items_sold": 460}, {"name": "New ListingApple Watch Series 6 44 mm Blue Aluminum Case with Deep Navy Sport Band...", "price": 25900, "status": "Brand New", "shipping": 1595, "free_returns": false, "items_sold": null}, {"name": "Apple Watch Series 4 - 40mm/44mm - All Case Colors - Black Sport Band - GPS/LTE", "price": 15299, "status": "Refurbished", "shipping": 0, "free_returns": true, "items_sold": 85}, {"name": "Apple Watch Series 1 - 38mm/42mm - Sport Band - Smartwatch - Very Good", "price": 5999, "status": "Refurbished", "shipping": 0, "free_returns": true, "items_sold": null}, {"name": "Apple Watch Series 2 38mm A1757 Aluminum Case Pink Sport Band GPS Version", "price": 8000, "status": "Pre-Owned", "shipping": 0, "free_returns": false, "items_sold": 0}, {"name": "Apple Watch Series 3 - 38mm/42mm - All Case Colors - Black Sport Band - GPS/LTE", "price": 12599, "status": "Refurbished", "shipping": 0, "free_returns": true, "items_sold": 40}, {"name": "NEW Apple Watch Series 3 GPS 38MM Silver Aluminum Case White Sport Band MTEY2LLA", "price": 19995, "status": "Brand New", "shipping": 0, "free_returns": true, "items_sold": 0}, {"name": "New ListingApple Watch Series 5 44mm Gold Aluminum Case White Sport Band GPS LTE Ships asap", "price": 18999, "status": "Pre-Owned", "shipping": 0, "free_returns": false, "items_sold": null}, {"name": "Genuine Apple Watch Series 2 42mm Aluminium Case Black Sport Band - Smartwatch", "price": 8899, "status": "Refurbished", "shipping": 0, "free_returns": true, "items_sold": null}, {"name": "Apple Watch SE 40mm Space Gray Aluminum Case with Black Sport Band", "price": 18995, "status": "Pre-Owned", "shipping": 0, "free_returns": true, "items_sold": 0}, {"name": "New ListingApple Watch Series 5 40mm Space Gray Aluminium Case with Black Sport Band - S/M", "price": 27500, "status": "Open Box", "shipping": 975, "free_returns": false, "items_sold": null}, {"name": "Apple Watch Series SE GPS w/ 40MM Gold Aluminum Case & Pink Sand Sport Band", "price": 22995, "status": "Refurbished", "shipping": 0, "free_returns": true, "items_sold": 0}, {"name": "", "price": null, "status": null, "shipping": null, "free_returns": false, "items_sold": null}, {"name": "NEW Apple Watch Series 3 38mm Gold Case with Pink Sand Sport Band GPS", "price": 15995, "status": "Open Box", "shipping": 0, "free_returns": true, "items_sold": 0}, {"name": "Apple Watch Series 6 40mm Gold Case Pink Sand Sport Band GPS + Cellular Pristine", "price": 34700, "status": "Open Box", "shipping": 0, "free_returns": true, "items_sold": 0}, {"name": "New ListingApple Watch Series 6 44mm Gold Aluminum Case with Pink Sand Sport Band - Regular", "price": 53000, "status": "Brand New", "shipping": 0, "free_returns": false, "items_sold": null}, {"name": "Apple Watch Series 5 - 40mm/44mm - All Case Colors - Black Sport Band - GPS/LTE", "price": 21599, "status": "Refurbished", "shipping": 0, "free_returns": true, "items_sold": 0}, {"name": "Apple Watch Series 5 40mm 44mm GPS + Cellular 4G LTE Gold Space Gray Silver ", "price": 26399, "status": "Refurbished", "shipping": null, "free_returns": true, "items_sold": 220}, {"name": "Apple Watch Series 6 - 40mm/44mm - All Case Colors - Black Sport Band - GPS/LTE", "price": 30599, "status": "Refurbished", "shipping": 0, "free_returns": true, "items_sold": 0}, {"name": "New ListingApple Watch Series 6 Cellular - Red - 40mm - Fully Functional PLEASE READ", "price": 20998, "status": "Pre-Owned", "shipping": 0, "free_returns": true, "items_sold": null}, {"name": "Apple Watch Series 4 (GPS + Cellular) 44mm Smartwatch - Good", "price": 17999, "status": "Pre-Owned", "shipping": 0, "free_returns": true, "items_sold": 425}, {"name": "Apple Watch Series 3 38mm 42mm GPS + WiFi Smart Watch, Rose Gold, Gray Silver!", "price": 10999, "status": "Refurbished", "shipping": 0, "free_returns": true, "items_sold": 152}, {"name": "Apple Watch Series 1 (42mm, Space Gray, Aluminum Case)", "price": 5995, "status": "Pre-Owned", "shipping": 0, "free_returns": false, "items_sold": 0}, {"name": "New ListingApple Watch Series 6 44mm Blue Aluminum Case Deep Navy Sport Band GPS WiFi", "price": 31900, "status": "Open Box", "shipping": 0, "free_returns": true, "items_sold": null}, {"name": "APPLE WATCH Series 5 LTE+GPS 40MM black", "price": 16599, "status": "Pre-Owned", "shipping": 0, "free_returns": false, "items_sold": 0}, {"name": "New ListingApple Watch SE 44mm GPS + Cellular ", "price": 18000, "status": "Pre-Owned", "shipping": 0, "free_returns": true, "items_sold": null}, {"name": "Apple Watch Series 3 Aluminum 38mm 42mm WiFi All Colors", "price": 11900, "status": "Refurbished", "shipping": null, "free_returns": true, "items_sold": null}, {"name": "Apple Watch Series 1 - 42mm WiFi Only - Aluminum ", "price": 5689, "status": "Pre-Owned", "shipping": 800, "free_returns": false, "items_sold": null}, {"name": "Apple Watch Series SE GPS w/ 40MM Silver Aluminum Case & White Sport Band", "price": 23995, "status": "Refurbished", "shipping": 0, "free_returns": true, "items_sold": 0}, {"name": "NEW Apple Watch Series 2 42mm GPS Space Gray Case with Black Sport Band", "price": 13995, "status": "Open Box", "shipping": 0, "free_returns": true, "items_sold": 0}, {"name": "Apple Watch Series 3 38mm Space Gray Alum/Black Band Model A 1860", "price": 7000, "status": "Pre-Owned", "shipping": 850, "free_returns": false, "items_sold": null}, {"name": "Apple Watch Series 2 - 38mm/42mm - Aluminum or SS Case - All Colors - Smartwatch", "price": 7999, "status": "Refurbished", "shipping": 0, "free_returns": true, "items_sold": 0}, {"name": "Apple Watch Series 6 40mm\u00a0Space Gray Case\u00a0Black Band GPS + Cellular Pristine", "price": 32900, "status": "Open Box", "shipping": 0, "free_returns": true, "items_sold": 0}, {"name": "Apple Watch SE 40mm Gold Case With Pink Sand Sport Band (GPS) PRISTINE IN BOX", "price": 23499, "status": "Open Box", "shipping": null, "free_returns": true, "items_sold": 586}, {"name": "Apple Watch Series 3 38 mm Silver Case White Band Smartwatch PRISTINE IN BOX", "price": 14999, "status": "Open Box", "shipping": 0, "free_returns": true, "items_sold": 1025}, {"name": "Apple Watch 42mm Series 3 GPS + Cellular with Sport Band MQK12LL/A - Very Good", "price": 14499, "status": "Refurbished", "shipping": 0, "free_returns": true, "items_sold": 400}, {"name": "Apple Watch Gen 3 Series 3 42mm Space Gray Aluminum - Black Sport Band MTF32LL/A", "price": 15500, "status": "Pre-Owned", "shipping": 0, "free_returns": true, "items_sold": 592}, {"name": "apple watch series 5 44mm cellular", "price": 29900, "status": "Pre-Owned", "shipping": 0, "free_returns": false, "items_sold": null}, {"name": "Apple Watch Series 5 44mm Space Gray Case Black Band - (MWVF2LL/A) Used", "price": 8800, "status": "Pre-Owned", "shipping": 0, "free_returns": false, "items_sold": null}, {"name": "Apple Watch Series 1 42mm Space Gray Aluminum Case Case Sport Band Smart Watch", "price": 6499, "status": "Pre-Owned", "shipping": 999, "free_returns": false, "items_sold": null}, {"name": "Apple Watch Series 4 44 mm Space Gray Aluminum Case (GPS)", "price": 8300, "status": "Pre-Owned", "shipping": 795, "free_returns": false, "items_sold": null}, {"name": "iWatch 42/40/44mm Bumper Protect Hard Case Cover Fr Apple Watch Series 6/SE5/4/3", "price": 497, "status": "Brand New", "shipping": null, "free_returns": false, "items_sold": 77}, {"name": "Apple Watch Series 6 Gps, 40mm Space Gray W/ Black Sport Band - Ref", "price": 29499, "status": "Refurbished", "shipping": 0, "free_returns": true, "items_sold": 0}, {"name": "Apple Watch Series 3 38mm Space Gray Aluminum Case GPS NO BAND ", "price": 9900, "status": "Pre-Owned", "shipping": 0, "free_returns": false, "items_sold": 0}, {"name": "New ListingApple Watch Hermes Series 6 44mm Stainless Steel (Does Not Include Leather Band)", "price": 81500, "status": "Pre-Owned", "shipping": 0, "free_returns": false, "items_sold": null}, {"name": "Apple Watch Series 3 38mm / 42mm  Aluminum GPS + GSM Cellular  Very Good", "price": 13995, "status": "Refurbished", "shipping": 0, "free_returns": true, "items_sold": 593}, {"name": "Apple Watch Series 2 38mm Space Gray Aluminum Case Black Sport Band - C Stock", "price": 6999, "status": "Pre-Owned", "shipping": 0, "free_returns": true, "items_sold": 0}, {"name": "Apple Watch Series 4 44 mm Space Gray Aluminum Case with Black Sport Band (GPS) ", "price": 16995, "status": "Pre-Owned", "shipping": 1595, "free_returns": false, "items_sold": null}, {"name": "New ListingApple Watch Series 2 38mm Stainless Steel Case GPS model MNP52LL/A", "price": 6999, "status": "Pre-Owned", "shipping": 600, "free_returns": false, "items_sold": null}, {"name": "Apple Watch Series 3 with GPS\u00a0", "price": 6000, "status": "Pre-Owned", "shipping": 1095, "free_returns": false, "items_sold": null}, {"name": "New ListingApple Watch Series 4, 44 mm Space Gray, with Black Sport Loop (GPS) + cables", "price": 5000, "status": "Pre-Owned", "shipping": 1625, "free_returns": false, "items_sold": null}, {"name": "Refurbished Apple Watch Series 1 38mm, 42mm No iCloud Account Ready to Use", "price": 6798, "status": "Refurbished", "shipping": 580, "free_returns": false, "items_sold": null}, {"name": "Apple\u00a0Watch Series\u00a03 (GPS, 38mm)Silver Aluminium Case wWhite Sport Band- Openbox", "price": 14039, "status": "Open Box", "shipping": 299, "free_returns": true, "items_sold": 0}, {"name": "New ListingApple Watch Series 3 42mm Smartwatch (GPS + Cellular, Silver Aluminum Case)", "price": 6900, "status": "Pre-Owned", "shipping": 1065, "free_returns": false, "items_sold": null}, {"name": "Apple Watch Series 4 Stainless Steel 40mm WiFi GPS Cellular 4G LTE Sport Blue", "price": 21500, "status": "Pre-Owned", "shipping": 0, "free_returns": false, "items_sold": null}, {"name": "Apple Watch SE (GPS, 40mm) - Silver Aluminum Case with White Sport Band", "price": 8400, "status": "Pre-Owned", "shipping": 872, "free_returns": true, "items_sold": null}, {"name": "Apple Watch SE (Aluminum, 40 mm, Kumquat Sport Loop, GPS) *New, Sealed*", "price": 29000, "status": "Brand New", "shipping": 1115, "free_returns": false, "items_sold": null}, {"name": "Apple Watch Series 3 - Rose Gold with Pink Sand Sport Band (GPS + Cellular)", "price": 12500, "status": "Pre-Owned", "shipping": 1000, "free_returns": false, "items_sold": null}, {"name": "New ListingApple Watch Series 4 44mm Space Black Stainless Steel Case (GPS & Cellular)", "price": 9900, "status": "Pre-Owned", "shipping": 1999, "free_returns": false, "items_sold": null}, {"name": "Apple Watch Series 4 44mm Silver Aluminum", "price": 16050, "status": "Pre-Owned", "shipping": 1465, "free_returns": false, "items_sold": null}, {"name": "New ListingApple Watch Series 5 44mm Aluminum case space gray color GPS version", "price": 22500, "status": "Open Box", "shipping": 0, "free_returns": false, "items_sold": null}, {"name": "Apple Watch Series 3 42mm Space Gray Case Black Sport Band GPS + Cellular", "price": 14499, "status": "Refurbished", "shipping": 0, "free_returns": true, "items_sold": 702}, {"name": "Apple Watch Series 2 - 38mm/42mm - Aluminum Case - Sport Band - iOS - Smartwatch", "price": 6999, "status": "Refurbished", "shipping": 0, "free_returns": true, "items_sold": 203}, {"name": "Apple Watch Series 4 GPS+LTE w/ 44MM Gold Aluminum Case & Pink Sand Sport Band", "price": 19995, "status": "Pre-Owned", "shipping": 0, "free_returns": true, "items_sold": 0}, {"name": "Apple Watch Gen 3 Series 3 38mm Silver Aluminum - White Sport Band MTEY2LL/A", "price": 13900, "status": "Pre-Owned", "shipping": 0, "free_returns": true, "items_sold": 694}, {"name": "New ListingApple Watch Series 6 Cell 44mm Space Gray Aluminum Case W/ New Black Sport Band", "price": 13550, "status": "Pre-Owned", "shipping": 1035, "free_returns": false, "items_sold": null}, {"name": "New ListingApple Watch Series 4 Nike+ 44 mm Space Gray Aluminum Case with Anthracite/Black", "price": 10000, "status": "Pre-Owned", "shipping": 2195, "free_returns": false, "items_sold": null}, {"name": "Apple Watch Series 6 40mm Gold Aluminum Case GPS", "price": 21400, "status": "Pre-Owned", "shipping": 1065, "free_returns": false, "items_sold": null}, {"name": "New ListingApple Watch Series 6 (GPS, 40mm) Aluminum Case with (Product) RED\ufeff - Sport Band", "price": 11250, "status": "Pre-Owned", "shipping": 872, "free_returns": true, "items_sold": null}, {"name": "Apple Watch Series SE 40mm/44mm A2353 A2354 Cellular + GPS", "price": 20999, "status": "Pre-Owned", "shipping": 0, "free_returns": true, "items_sold": 46}, {"name": "New ListingAPPLE WATCH SERIES 3 (GPS) 42MM SPACE GRAY ALUMINUM CASE | MTF32LL/A ", "price": 6600, "status": "Pre-Owned", "shipping": 1222, "free_returns": true, "items_sold": null}, {"name": "apple watch series 6 44mm gps cellular", "price": 26200, "status": "Pre-Owned", "shipping": 1199, "free_returns": false, "items_sold": null}, {"name": "Apple Watch Series 1 - 38mm - Gray / Black - Sport Band Smartwatch - Excellent", "price": 7999, "status": "Open Box", "shipping": 0, "free_returns": true, "items_sold": 0}, {"name": "Apple Watch Series 3 42mm Stainless Steel Soft White Sport Band GPS Cellular CIB", "price": 13000, "status": "Pre-Owned", "shipping": 1800, "free_returns": false, "items_sold": null}, {"name": "Apple Watch 1st Gen. 7000 Series Sport - Wi Fi - Smartwatch - Very Good", "price": 6499, "status": "Refurbished", "shipping": 0, "free_returns": true, "items_sold": null}, {"name": "Apple Watch Series 4 44 mm Space Black Stainless Steel Case with Black Sport...", "price": 12750, "status": "Pre-Owned", "shipping": 1595, "free_returns": false, "items_sold": null}, {"name": "Apple Watch Series SE with GPS, 44 mm, Space Gray Aluminum Case", "price": 15250, "status": "Pre-Owned", "shipping": 1095, "free_returns": false, "items_sold": null}, {"name": "Apple Watch Series 2 Edition 38mm White ceramic, Cloud Sports Band 8GB Wi-Fi", "price": 14999, "status": "Pre-Owned", "shipping": 0, "free_returns": true, "items_sold": 0}, {"name": "Apple Watch SE - 40mm/44mm - Silver/Gold/Space Gray - Black Sport Band - GPS/LTE", "price": 21599, "status": "Refurbished", "shipping": 0, "free_returns": true, "items_sold": 0}, {"name": "", "price": null, "status": null, "shipping": null, "free_returns": false, "items_sold": null}, {"name": "NEW Apple Watch Series 3 38mm Gold Case & Pink Sand Sport Band GPS", "price": 15995, "status": "Open Box", "shipping": 0, "free_returns": true, "items_sold": 0}, {"name": "Apple Watch Series 5 GPS+LTE w/ 40MM Space Gray Aluminum Case & Black Sport Band", "price": 28995, "status": "Refurbished", "shipping": 0, "free_returns": true, "items_sold": 0}, {"name": "Apple Watch Series 6 \ud83c\udf4e GPS + Cellular \u231a 40mm / 44mm Aluminum Case w/ Sport Band", "price": 32999, "status": "Refurbished", "shipping": 0, "free_returns": true, "items_sold": 18}, {"name": "Apple Watch Series 1 42mm Aluminum Case White Sport Band - (MNNL2LL/A)", "price": 9888, "status": "Refurbished", "shipping": 0, "free_returns": false, "items_sold": 0}, {"name": "New ListingApple Watch Series 5 44mm Aluminum case space gray color GPS version", "price": 22500, "status": "Open Box", "shipping": 0, "free_returns": false, "items_sold": null}, {"name": "Apple Watch Series 5 44mm Gold Aluminum MWT52LL/A-CRACKED Fully Functional", "price": 13500, "status": "Pre-Owned", "shipping": 925, "free_returns": false, "items_sold": 0}, {"name": "New ListingApple Watch Series 5 44mm Gold Aluminum Case White Sport Band GPS LTE Ships asap", "price": 20999, "status": "Pre-Owned", "shipping": 0, "free_returns": false, "items_sold": null}, {"name": "Apple Watch 6 44mm Silver Stainless Steel -Charcoal Braided Solo Loop 11", "price": 45999, "status": "Pre-Owned", "shipping": null, "free_returns": false, "items_sold": null}, {"name": "Apple Watch Series 4 40mm A1975 LTE GPS Aluminum Case SILVER", "price": 14000, "status": "Pre-Owned", "shipping": 870, "free_returns": false, "items_sold": null}, {"name": "New ListingApple Watch Series 5 Nike 40mm Silver Aluminum Case - MX372LL/A", "price": 30000, "status": "Open Box", "shipping": 1700, "free_returns": false, "items_sold": null}, {"name": "Apple Watch 38mm Series 3 GPS + Cellular with Sport Band MQJN2LL/A - Very Good", "price": 13999, "status": "Refurbished", "shipping": 0, "free_returns": true, "items_sold": 264}, {"name": "Apple Watch Series 7 45mm Aluminum Case with Sport Band - Midnight - GPS - FS", "price": 61999, "status": "Brand New", "shipping": 0, "free_returns": false, "items_sold": 0}, {"name": "Apple Watch Series 6 GPS 44mm Gold Aluminum Case Black Solo Loop Band", "price": 24000, "status": "Pre-Owned", "shipping": 0, "free_returns": false, "items_sold": 0}, {"name": "Apple Watch Series 4 GPS 44MM Space Gray  Case & Black Band Bad Condition", "price": 17000, "status": "Refurbished", "shipping": 0, "free_returns": true, "items_sold": 86}, {"name": "Apple Watch SE GPS 40mm Gold Aluminum Case With Pink Sand Sport Band MYDN2LL/A", "price": 25989, "status": "Brand New", "shipping": 0, "free_returns": true, "items_sold": 60}, {"name": "Apple\u00a0Watch Series 6 (GPS,40mm)Blue Aluminum Case wDeep Navy Sport Band Preowned", "price": 27499, "status": "Pre-Owned", "shipping": 299, "free_returns": true, "items_sold": 0}, {"name": "Apple Watch Nike+ Series 3 - 38mm/42mm - All Colors - Black Sport Band - GPS/LTE", "price": 14399, "status": "Refurbished", "shipping": 0, "free_returns": true, "items_sold": 0}, {"name": "Apple Watch Series 3 42mm Gold Case Pink Sand Sport Band GPS + Cellular", "price": 15999, "status": "Refurbished", "shipping": 0, "free_returns": true, "items_sold": 0}, {"name": "NEW Apple Watch Series 3 38mm Space Gray Aluminum Case (GPS+Cellular) Unlocked", "price": 17995, "status": "Open Box", "shipping": 0, "free_returns": true, "items_sold": 0}, {"name": "New ListingApple Watch Series 6 Stainless Steel Case 44mm (GPS + Cellular) M07R3LL/A ", "price": 44999, "status": "Pre-Owned", "shipping": 1116, "free_returns": true, "items_sold": null}, {"name": "New ListingApple Watch Series 5 Nike LTE 44mm Space Gray", "price": 21000, "status": "Pre-Owned", "shipping": 0, "free_returns": false, "items_sold": null}, {"name": "apple watch series 5 44mm cellular unlocked", "price": 16750, "status": "Pre-Owned", "shipping": 1000, "free_returns": false, "items_sold": null}, {"name": "New ListingApple Watch Series 5 Edition 44mm Titanium", "price": 35000, "status": "Pre-Owned", "shipping": 0, "free_returns": false, "items_sold": null}, {"name": "Apple Watch Nike+ Series 2 42mm Space Gray Black band Good Used Condition", "price": 7035, "status": "Pre-Owned", "shipping": 1065, "free_returns": false, "items_sold": null}, {"name": "New ListingApple Watch Series 6 44mm Space Gray Aluminum Case with Black Sport Band LTE", "price": 19700, "status": "Pre-Owned", "shipping": 1595, "free_returns": false, "items_sold": null}, {"name": "Apple Watch Series 2 Sport Band - 38mm - Space Gray/Black - WiFi - Smartwatch", "price": 6999, "status": "Pre-Owned", "shipping": 0, "free_returns": true, "items_sold": 0}, {"name": "New ListingApple Watch Series 5 40mm Space Gray Aluminium Case with Black Sport Band - S/M", "price": 18900, "status": "Pre-Owned", "shipping": 550, "free_returns": false, "items_sold": null}, {"name": "Apple Watch Series 5 40mm Space Gray Aluminium Case (GPS + Cellular)", "price": 15801, "status": "Pre-Owned", "shipping": 0, "free_returns": true, "items_sold": null}, {"name": "Apple Watch Series 4 40mm Silver Aluminum Case, White Sport Band (GPS + CELL)", "price": 16999, "status": "Pre-Owned", "shipping": 0, "free_returns": true, "items_sold": 0}, {"name": "Apple Watch 1st Gen. 7000 Series Sport - Wi Fi - Smartwatch", "price": 5499, "status": "Refurbished", "shipping": 0, "free_returns": true, "items_sold": null}, {"name": "NEW Apple Watch Series 3 38MM GPS Space Gray Aluminum Black Sport Band MTF02LL/A", "price": 18995, "status": "Brand New", "shipping": null, "free_returns": true, "items_sold": 0}, {"name": "New Listingapple watch series 3 38mm Stainless Steel Case gps cellular", "price": 9900, "status": "Pre-Owned", "shipping": 1065, "free_returns": false, "items_sold": null}, {"name": "New ListingApple Watch SE Nike 40mm Space Gray Aluminum Case with Anthracite/Black Sport", "price": 13500, "status": "Brand New", "shipping": 1465, "free_returns": false, "items_sold": null}, {"name": "apple watch series 5 44mm", "price": 21000, "status": "Pre-Owned", "shipping": 540, "free_returns": false, "items_sold": 0}, {"name": "Apple Watch Series 1, Good condition.", "price": 3700, "status": "Pre-Owned", "shipping": 1000, "free_returns": false, "items_sold": null}, {"name": "Apple Watch SE 40mm Silver Case White Smart Watch - (MYDM2LLA)", "price": 20900, "status": "Open Box", "shipping": 1065, "free_returns": false, "items_sold": null}, {"name": "New ListingApple Watch Series 3 38mm Space Gray Case Black Metal Band - FLAWLESS screen!", "price": 11000, "status": "Pre-Owned", "shipping": 0, "free_returns": false, "items_sold": null}, {"name": "Apple Watch Series 1 38mm Silver Aluminum Case White Sport Band - MNNG2LL/A", "price": 7499, "status": "Refurbished", "shipping": 0, "free_returns": true, "items_sold": 0}, {"name": "Apple Watch Series 5- 40mm/44mm -Cellular - Stainless Steel/ Various Conditions", "price": 29999, "status": "Refurbished", "shipping": 0, "free_returns": true, "items_sold": null}, {"name": " Apple Watch SE GPS 44mm Aluminum Case White Sport Band Silver MYDQ2LL/A", "price": 20699, "status": "Pre-Owned", "shipping": 0, "free_returns": true, "items_sold": null}, {"name": "Apple Watch3 42mm Black Stainless Steel Case Gps+cellular Real Carbon Fiber", "price": 30000, "status": "Pre-Owned", "shipping": 1500, "free_returns": false, "items_sold": null}, {"name": "Apple\u00a0Watch Series 6 (GPS, 40mm) - Gold Aluminum Case with Pink Sand Sport Band", "price": 22288, "status": "Pre-Owned", "shipping": 872, "free_returns": true, "items_sold": null}, {"name": "Apple Watch Series 3 Space Gray (Cracked Screen)", "price": 5100, "status": "Pre-Owned", "shipping": 0, "free_returns": false, "items_sold": null}, {"name": "New ListingNEW Apple Watch Series 6 GPS 40mm Blue Aluminium Case Deep Navy Sport Band ", "price": 11250, "status": "Brand New", "shipping": 500, "free_returns": false, "items_sold": null}, {"name": "GENTLY Used Apple Watch Series 2 42mm Silver Aluminum Case - 10 Bands INCLUDED", "price": 7000, "status": "Pre-Owned", "shipping": 1595, "free_returns": false, "items_sold": null}, {"name": "Apple Watch Series 5 40mm Aluminum Gold Case Pink Sand Sport Band - MWV72LL/A", "price": 14800, "status": "Open Box", "shipping": 0, "free_returns": false, "items_sold": null}, {"name": "Apple Watch Series 5 Stainless Steel 40mm WiFi GPS Cellular, No Band", "price": 10250, "status": "Pre-Owned", "shipping": 1000, "free_returns": false, "items_sold": null}, {"name": "Apple Watch Series 5 44mm GPS + Cellular Space Gray Unlocked", "price": 19999, "status": "Pre-Owned", "shipping": 1580, "free_returns": false, "items_sold": null}, {"name": "Apple Watch Series 4 40mm 44mm GPS + Cellular Smart Watch", "price": 16999, "status": "Refurbished", "shipping": 0, "free_returns": true, "items_sold": 160}, {"name": "Apple Watch Series 4 44 mm Stainless Steel Case with White Sport Band (GPS +...", "price": 29900, "status": "Pre-Owned", "shipping": 1595, "free_returns": false, "items_sold": null}, {"name": "Apple Watch SE (GPS, 40mm) - Space Gray Aluminum Case with Black Sport Band", "price": 10250, "status": "Pre-Owned", "shipping": 872, "free_returns": true, "items_sold": null}, {"name": "Apple Watch Series 3 38mm Silver Aluminum White Sport Band ", "price": 13500, "status": "Pre-Owned", "shipping": 800, "free_returns": false, "items_sold": null}, {"name": "Apple Watch Series 3 38mm Space Gray Aluminum Case Black Sport Band Lv Cellular", "price": 9900, "status": "Pre-Owned", "shipping": 1695, "free_returns": false, "items_sold": null}, {"name": "apple iwatch series 5 40mm", "price": 22500, "status": "Pre-Owned", "shipping": 415, "free_returns": false, "items_sold": null}, {"name": "Apple Watch Series 2 - 38mm/42mm - Aluminum Case - All Colors - Smartwatch", "price": 6999, "status": "Pre-Owned", "shipping": 0, "free_returns": true, "items_sold": 89}, {"name": "New ListingApple Watch Series 6 44 mm Blue Aluminum Case with Deep Navy Sport Band...", "price": 31000, "status": "Brand New", "shipping": 0, "free_returns": false, "items_sold": null}, {"name": "Apple Watch Series 4 44mm GPS and Cellular Cracked screen, AT&T cellular.", "price": 9999, "status": "Pre-Owned", "shipping": 599, "free_returns": false, "items_sold": 0}, {"name": "Apple Watch SE GPS + Cellular 44mm Space Gray Aluminum Case - Black Sport Band", "price": 19000, "status": "Pre-Owned", "shipping": 0, "free_returns": false, "items_sold": null}, {"name": "Apple Watch Series 5 (GPS + Cellular) 40mm Smartwatch - Very Good", "price": 24999, "status": "Refurbished", "shipping": 0, "free_returns": true, "items_sold": 116}, {"name": "Apple Watch Series 4 (GPS + Cellular) 44mm Space Gray Aluminum Case", "price": 18900, "status": "Pre-Owned", "shipping": 1270, "free_returns": false, "items_sold": null}, {"name": "Apple Watch Series 3 42 mm Gray Case Black Aluminium Smartwatch Fair", "price": 12499, "status": "Pre-Owned", "shipping": 0, "free_returns": true, "items_sold": 0}, {"name": "New ListingApple\u00a0Watch Series 6 (GPS, 40mm) - Blue Aluminum Case with Deep Navy Sport Band", "price": 2150, "status": "Pre-Owned", "shipping": 872, "free_returns": true, "items_sold": null}, {"name": "New ListingAPPLE WATCH NIKE+ 42MM SILVER ALUMINIUM CASE | MQLC2LL/A | BLACK", "price": 3600, "status": "Pre-Owned", "shipping": 1222, "free_returns": true, "items_sold": null}, {"name": "Apple Watch Series 4 40 mm Space Gray Aluminum Black Sport Band (GPS + Cellular)", "price": 25999, "status": "Brand New", "shipping": 0, "free_returns": true, "items_sold": 0}, {"name": "NEW Apple Watch Series 4 44mm Space Gray Case with Black Band GPS + Cellular", "price": 27995, "status": "Open Box", "shipping": 0, "free_returns": true, "items_sold": 0}, {"name": "New ListingApple Watch Series 3 GPS 42mm Stainless Steel Case & Band. Silver Smartwatch.", "price": 26500, "status": "Brand New", "shipping": 1270, "free_returns": false, "items_sold": null}, {"name": "", "price": null, "status": null, "shipping": null, "free_returns": false, "items_sold": null}, {"name": "Apple Watch SE \ud83c\udf4e WiFi + 4G Cellular \u231a 40mm 44mm Aluminum Case Sport Loop / Band", "price": 17999, "status": "Open Box", "shipping": 0, "free_returns": true, "items_sold": 15}, {"name": "Apple Watch Gen 6 Series 6 40mm Silver Aluminum - White Sport Band M02N3LL/A", "price": 31700, "status": "Refurbished", "shipping": 0, "free_returns": true, "items_sold": 0}, {"name": " Apple Watch SE 40mm Gold Aluminum Case with Pink Sand Sport Band - Regular (GPS", "price": 18900, "status": "Pre-Owned", "shipping": 0, "free_returns": false, "items_sold": 0}, {"name": "Apple Watch Series 1 MP032LLA 42mm Aluminum Case Smartwatch - Grey", "price": 9888, "status": "Refurbished", "shipping": 0, "free_returns": false, "items_sold": 0}, {"name": "Apple Watch Series 4 40 mm Space Gray Aluminum Black Sport Band (GPS + Cellular)", "price": 25999, "status": "Brand New", "shipping": 0, "free_returns": true, "items_sold": 0}, {"name": "Apple Watch se 44mm Aluminum & Ceramic Case With Pink Sand Sport Band", "price": 21999, "status": "Pre-Owned", "shipping": 0, "free_returns": true, "items_sold": null}, {"name": "apple watch series 3 38", "price": 7200, "status": "Pre-Owned", "shipping": 460, "free_returns": false, "items_sold": null}, {"name": "New ListingApple Watch Series 6 Cell 44mm Silver Aluminum Case W/ New White Sport Band", "price": 17500, "status": "Pre-Owned", "shipping": 880, "free_returns": false, "items_sold": null}, {"name": "\ud83d\udd252021 Apple Watch SE Nike Sport Band 40mm SpaceGray+Black -GPS- >>>Beautiful<<<", "price": 16750, "status": "Open Box", "shipping": 1270, "free_returns": false, "items_sold": null}, {"name": "Apple Watch Nike Series 6 GPS+ Cellular 44mm Space Gray Watch Blk Band", "price": 34000, "status": "Pre-Owned", "shipping": 2170, "free_returns": false, "items_sold": null}, {"name": "Apple Watch Series 6 44mm Aluminum Case with Sport Band - Red GPS+ CELL", "price": 20250, "status": "Pre-Owned", "shipping": 925, "free_returns": false, "items_sold": null}, {"name": "New ListingNEW Apple Watch Series 6 GPS 40mm Blue Aluminium Case Deep Navy Sport Band ", "price": 11250, "status": "Brand New", "shipping": 500, "free_returns": false, "items_sold": null}, {"name": "New ListingApple Watch Series 5 40mm Silver Aluminum Case with Khaki Sport Loop - S/M", "price": 22999, "status": "Pre-Owned", "shipping": 829, "free_returns": false, "items_sold": null}, {"name": "NEW Apple\u00a0Watch Series 3 (GPS) 42mm Space Gray Aluminum Case w/ Black Sport Band", "price": 27950, "status": "Brand New", "shipping": 0, "free_returns": true, "items_sold": null}, {"name": "Apple Watch Series 6 GPS + LTE 40MM Space Gray Aluminum Case & Black Sport Band", "price": 31995, "status": "Pre-Owned", "shipping": 0, "free_returns": true, "items_sold": 0}, {"name": "Apple Watch SE (GPS) 44mm Aluminum Case Black Sport Band - Space Gray MYDT2LL/A", "price": 21049, "status": "Pre-Owned", "shipping": 0, "free_returns": true, "items_sold": null}, {"name": "Apple Watch Series SE GPS+LTE w/ 44MM Space Gray Aluminum Case, Black Sport Band", "price": 28995, "status": "Refurbished", "shipping": 0, "free_returns": true, "items_sold": 0}, {"name": "Apple Watch Series 3 (A1859) 42mm Space Gray, GPS, Aluminum, Original Packaging", "price": 12900, "status": "Pre-Owned", "shipping": 795, "free_returns": false, "items_sold": null}, {"name": "NEW Apple Watch Series 3 38mm Space Gray Aluminum Case & Black Sport Band", "price": 15995, "status": "Open Box", "shipping": 0, "free_returns": true, "items_sold": 0}, {"name": "Apple Watch Series 5 40mm Rose Gold GPS + Cellular Smart Watch", "price": 21999, "status": "Refurbished", "shipping": 0, "free_returns": true, "items_sold": null}, {"name": "MINT!! Apple Watch SE 44mm Space Gray Aluminum Case GPS Black Sport Band a2352 ", "price": 11650, "status": "Pre-Owned", "shipping": 0, "free_returns": false, "items_sold": null}, {"name": "Apple Watch Series 6 44MM GPS Aluminum Case w/ White Sport Band M00D3LL/A", "price": 34900, "status": "Open Box", "shipping": null, "free_returns": true, "items_sold": 0}, {"name": "Apple Watch Series 4 40 mm Silver Aluminum Case (GPS + Cellular)", "price": 9100, "status": "Pre-Owned", "shipping": 1595, "free_returns": false, "items_sold": null}, {"name": "\ud83d\udd252021 Apple Watch Series 6 GPS Gray/Silver/Gold 40/44mm Blue/Pink/Red SportBand", "price": 38275, "status": "Brand New", "shipping": 0, "free_returns": true, "items_sold": 161}, {"name": "Apple Watch Series 4 44 mm Space Gray Aluminum Case with Black Sport Band (GPS)", "price": 22500, "status": "Open Box", "shipping": 0, "free_returns": false, "items_sold": null}, {"name": "New ListingApple Watch Series 7 41mm Aluminum Case with Sport Band Black GPS + Cellular FS", "price": 45999, "status": "Open Box", "shipping": 0, "free_returns": false, "items_sold": null}, {"name": "apple watch series 6 44mm", "price": 5400, "status": "Pre-Owned", "shipping": 475, "free_returns": false, "items_sold": null}, {"name": "New ListingApple Watch Series 3 38 mm Silver Aluminum Case White Sport Band Smartwatch\u00a0", "price": 13500, "status": "Pre-Owned", "shipping": 1270, "free_returns": false, "items_sold": null}, {"name": "Apple Watch Nike+ Series 4 - 40mm/44mm - Two Colors - Black Sport Band - GPS/LTE", "price": 16199, "status": "Refurbished", "shipping": 0, "free_returns": true, "items_sold": 0}, {"name": "Apple Watch Series 4 -40mm/44mm- CELL- Stainless Steel/ Various Conditions", "price": 22999, "status": "Refurbished", "shipping": 0, "free_returns": true, "items_sold": 0}, {"name": "Apple Watch Series SE 44mm Space Gray Aluminum (GPS+Cellular) MYER2LL/A", "price": 21999, "status": "Pre-Owned", "shipping": 0, "free_returns": true, "items_sold": 0}, {"name": "Apple Watch Series 6 (GPS, 44mm) Silver Aluminum Case with White Sport Band", "price": 5800, "status": "Pre-Owned", "shipping": 872, "free_returns": true, "items_sold": null}, {"name": "Apple Watch Series 2 - 38mm - Silver Case - White Sport Band (GPS)", "price": 7999, "status": "Refurbished", "shipping": 0, "free_returns": true, "items_sold": 160}, {"name": "Apple Watch Series 6 40mm\u00a0Silver Aluminum Case White Sport Band\u00a0\u00a0GPS + Cellular", "price": 35999, "status": "Open Box", "shipping": null, "free_returns": true, "items_sold": 0}, {"name": "Apple Watch Series 5 Nike 44mm Silver Aluminum Case with Pure Platinum/Black...", "price": 24500, "status": "Pre-Owned", "shipping": 1800, "free_returns": false, "items_sold": null}, {"name": "New ListingApple Watch Series 3 38 mm Gray Case Black Aluminium Smartwatch - MTF02LLA", "price": 19800, "status": "Brand New", "shipping": 550, "free_returns": false, "items_sold": null}, {"name": "Apple Watch Series 3 38mm Silver Aluminum Case with White Sport Band GPS Only", "price": 10100, "status": "Pre-Owned", "shipping": 699, "free_returns": false, "items_sold": null}, {"name": "New ListingApple Watch series 3 (Space grey- 38mm)", "price": 13999, "status": "Pre-Owned", "shipping": 0, "free_returns": false, "items_sold": null}, {"name": "Apple Watch Series 6 40mm Gold stainless steel", "price": 57500, "status": "Pre-Owned", "shipping": 0, "free_returns": false, "items_sold": null}, {"name": "Apple Watch Series 6 40MM GPS Aluminum Case Only Used Please Read", "price": 24499, "status": "Pre-Owned", "shipping": 0, "free_returns": true, "items_sold": 0}, {"name": "Apple Watch Series 3 42 mm Gray Case Black Aluminium Smartwatch PRISTINE IN BOX", "price": 16499, "status": "Open Box", "shipping": 0, "free_returns": true, "items_sold": 1314}, {"name": "New ListingApple Watch SE 44mm Space Gray Aluminum Case Midnight Sport Band GPS SEALED", "price": 28500, "status": "Brand New", "shipping": 0, "free_returns": false, "items_sold": null}, {"name": "New ListingApple Watch Series 3 42mm Gray Aluminum (GPS+Cellular) MUST READ DESCRIPTION!", "price": 104, "status": "Pre-Owned", "shipping": 0, "free_returns": true, "items_sold": null}, {"name": "Apple Watch Series 6 40mm GPS PRODUCT(RED) Sport Band M00A3LL/A", "price": 29900, "status": "Open Box", "shipping": null, "free_returns": true, "items_sold": null}, {"name": "Apple Watch SE", "price": 10250, "status": "Pre-Owned", "shipping": 475, "free_returns": false, "items_sold": null}, {"name": "Apple Watch Series 6 40mm Aluminum Case Red Sport Band Smart Watch (M00A3LL/A)", "price": 27998, "status": "Open Box", "shipping": 0, "free_returns": true, "items_sold": 0}, {"name": "Apple Watch Series 5 40mm Space Gray Aluminium Case with Black Sport Band - S/M", "price": 10700, "status": "Pre-Owned", "shipping": 550, "free_returns": false, "items_sold": null}, {"name": "New ListingApple Watch Series 4 44 mm Gold Aluminum Case with Black Sport Band GPS 44mm", "price": 16900, "status": "Pre-Owned", "shipping": 0, "free_returns": false, "items_sold": 0}, {"name": "New ListingApple watch series 5 (40mm silver aluminum)", "price": 16000, "status": "Open Box", "shipping": 700, "free_returns": false, "items_sold": null}, {"name": "Apple Watch Series 3 38mm Space Gray Excellent Used Condition", "price": 7800, "status": "Pre-Owned", "shipping": 0, "free_returns": false, "items_sold": null}, {"name": "Apple Watch SE 40mm Space Gray Case With Black Sport Band (GPS) PRISTINE IN BOX", "price": 23499, "status": "Open Box", "shipping": null, "free_returns": true, "items_sold": 690}, {"name": "Apple Watch Series 3 38mm Gold Aluminium Case with Pink Sand Sport Band (GPS)", "price": 3600, "status": "Pre-Owned", "shipping": 1176, "free_returns": false, "items_sold": null}, {"name": "apple watch se", "price": 19500, "status": "Pre-Owned", "shipping": 0, "free_returns": false, "items_sold": null}, {"name": "Apple Watch SE 40mm Space Gray GPS Aluminum Case with Sport Loop GRADE A", "price": 19799, "status": "Pre-Owned", "shipping": 0, "free_returns": true, "items_sold": null}, {"name": "Apple Watch Series 4 40mm 44mm GPS Aluminum Space Gray Silver Gold Smartwatch", "price": 18997, "status": "Refurbished", "shipping": 0, "free_returns": true, "items_sold": 0}, {"name": "New ListingApple Watch Series 6 GPS, 40mm Space Gray Aluminum Case with Black Sport Band", "price": 27000, "status": "Open Box", "shipping": 0, "free_returns": false, "items_sold": null}, {"name": "New Listingapple watch series 5 nike 44mm gps cellular", "price": 22500, "status": "Pre-Owned", "shipping": 1000, "free_returns": false, "items_sold": null}, {"name": "Apple Watch Series 6 44mm Gold Aluminum Case with Pink Sand Sport Band - Regular", "price": 17000, "status": "Pre-Owned", "shipping": 1465, "free_returns": false, "items_sold": null}, {"name": "apple watch series 3 38mm silver aluminum", "price": 6100, "status": "Pre-Owned", "shipping": 955, "free_returns": false, "items_sold": 0}, {"name": "Apple Watch Series 3 GPS + Cellular, 42mm Space Gray Aluminum Case", "price": 13500, "status": "Pre-Owned", "shipping": 1595, "free_returns": false, "items_sold": null}, {"name": "New ListingApple Watch Series 5 Aluminum 44mm ", "price": 12600, "status": "Pre-Owned", "shipping": 1000, "free_returns": false, "items_sold": null}, {"name": "Apple Watch Series 5 40mm Gold Aluminum GPS, Cellular, Wifi Pink Sand Sport Band", "price": 14900, "status": "Pre-Owned", "shipping": 1465, "free_returns": false, "items_sold": null}, {"name": "Apple Watch Series 6 40mm Silver w/ White Sport Band Bluetooth 5GHz WiFi Fitness", "price": 17250, "status": "Pre-Owned", "shipping": 1035, "free_returns": true, "items_sold": null}, {"name": "New ListingApple Watch Series 3 38mm Space Gray Aluminum Case Black Sport Band Smart Watch ", "price": 13253, "status": "Brand New", "shipping": 500, "free_returns": false, "items_sold": null}, {"name": "Apple Watch Series 4 GPS 40MM Gold Aluminum Case & Pink Sport Band Bad Condition", "price": 17500, "status": "Refurbished", "shipping": 0, "free_returns": true, "items_sold": 0}, {"name": "NEW Apple Watch Series 3 38mm Space Gray Aluminum Case GPS + Cellular (Unlocked)", "price": 17995, "status": "Open Box", "shipping": 0, "free_returns": true, "items_sold": 0}]